Workbook

Sheet Commenti coding
A1: Topic / dimensione | B1: Codifica finale | C1: Razionale di scoring / limiti
A2: Foundation | B2: 1 | C2: La DEIA è assente o compare solo in modo episodico, ad esempio in una dichiarazione valoriale o nella lettera del CEO, senza collegamenti a strategia, policy, responsabilità o obiettivi.
A3: Foundation | B3: 2 | C3: Esiste un richiamo generale a diversità/inclusione nei valori o nella people strategy, ma il presidio resta narrativo: non sono chiariti governance, responsabilità, policy dedicate o obiettivi misurabili.
A4: Foundation | B4: 3 | C4: La DEIA è riconoscibile nella strategia o nella governance e sono presenti policy, responsabilità o iniziative dedicate, ma manca almeno uno degli elementi che rendono il presidio pienamente strutturato, come target, KPI di avanzamento o outcome. Esempio: DEI policy e council presenti, ma senza un set completo di risultati misurati.
A5: Foundation | B5: 4 | C5: La DEIA è formalmente integrata in strategia, valori e governance ed è supportata da policy, responsabilità chiare, iniziative, KPI/target e risultati rendicontati. Esempio: sezione DEIA dedicata con organo responsabile, obiettivi pluriennali e monitoraggio periodico dei risultati.
A6: Retention & Onboarding | B6: 1 | C6: Non emergono evidenze di criteri DEIA nei processi di recruiting, onboarding o retention, oppure compaiono solo riferimenti isolati e non collegati ai processi HR.
A7: Retention & Onboarding | B7: 2 | C7: L'organizzazione dichiara di voler garantire selezioni eque o inclusive, ma non descrive in modo concreto strumenti, processi o controlli applicati a recruiting, onboarding e retention. Esempio: semplice richiamo a 'pari opportunità' nelle job vacancy.
A8: Retention & Onboarding | B8: 3 | C8: Sono documentate pratiche inclusive in alcune fasi del ciclo HR, come recruiting, onboarding, talent review o succession planning, ma mancano KPI o outcome specifici su assunzioni, retention, promozioni o mobilità dei gruppi sottorappresentati.
A9: Retention & Onboarding | B9: 4 | C9: Recruiting, onboarding e retention sono gestiti con processi DEIA formalizzati e monitorati tramite KPI/target e risultati. Esempio: tassi di hiring, turnover, retention o promotion disaggregati per genere/altre dimensioni, obiettivi di miglioramento e azioni correttive.
A10: Employment | B10: 1 | C10: Le condizioni di lavoro e le pari opportunità non sono affrontate in chiave DEIA o sono citate solo in modo occasionale senza evidenze su rappresentanza, accessibilità, welfare o equità retributiva.
A11: Employment | B11: 2 | C11: Vengono descritte iniziative generali su welfare, benessere o pari opportunità, ma senza un focus DEIA chiaro né dati sufficienti a valutarne copertura ed efficacia.
A12: Employment | B12: 3 | C12: Sono presenti evidenze specifiche su condizioni di lavoro e pari opportunità, ad esempio pay equity, rappresentanza, benefit, flessibilità o accessibilità, con alcuni KPI; il quadro resta però parziale o non accompagnato da target/outcome sistematici.
A13: Employment | B13: 4 | C13: La disclosure copre in modo strutturato condizioni di lavoro e opportunità con policy, azioni, KPI, target e risultati. Esempio: gender pay gap misurato annualmente, obiettivo di pay equity, dati su rappresentanza e benefit e verifica dell'avanzamento.
... A73: Aspetto fisico | B73: 4 | C73: L'organizzazione affronta esplicitamente i bias legati all'aspetto fisico con policy, formazione, monitoraggio e risultati misurabili. È un livello raro: richiede evidenze specifiche e non può essere assegnato sulla sola base di clausole generali di non-discriminazione.

Sheet Note_1
A1: Note metodologiche - Qualitative Content Analysis DEIA
A2: Data analisi | B2: 2026-07-01
A3: Perimetro | B3: Analisi dei tre report allegati e del foglio Dataset_reporting; nessuna fonte web esterna utilizzata.
A4: Criteri applicati | B4: Codifica item-by-item su scala 1-4: 1 assente/episodico; 2 generico/narrativo; 3 specifico o con KPI parziali; 4 strutturato con policy, azioni, KPI, target, outcome o responsabilità chiaramente attribuibili.
A5: Assunzioni | B5: La colonna "Supply Chain" è stata interpretata come presidio DEIA/sociale della catena del valore; la colonna duplicata "Supply chain" come presenza più specifica di supplier diversity/procurement inclusivo. I punteggi alti non sono stati assegnati per sole menzioni generiche.
A6: Limiti | B6: P.IVA compilata solo se presente nel report. Link DEIA lasciato vuoto perché non è stato rilevato un link DEIA specifico nei documenti. Il report Fater è un documento di sintesi: alcune pratiche potrebbero esistere ma non sono state codificate se non documentate.
A8: Azienda | B8: Principali evidenze | C8: Principali criticità/gap | D8: Pagine chiave | E8: Score temi | F8: Score dimensioni
A9: 4BILD / Bild Distribuzione S.p.A. | B9: Policy D&I e parità di genere, certificazione UNI/PdR 125, non discriminazione e monitoring annuale, KPI workforce per genere/età, Accademia e iniziative comunitarie. | C9: Poche evidenze su supplier diversity, religione, disabilità, etnia, LGBTQIA+, aspetto fisico e inclusive design/end-users. | D9: pp. 8, 16-17, 22-23, 30-33, 54-67, 72-73, ultima pagina P.IVA | E9: =[1]Dataset_reporting!U2 -> 3 | F9: =[1]Dataset_reporting!AD2 -> 1.75
A10: Fater S.p.A. | B10: KPI sociali e target su pay gap, survey interna, gender balance e comunità; certificazione parità di genere; report accessibile; rating fornitori ESG/SA8000. | C10: Disclosure sintetica; formazione DEIA non documentata; supplier diversity specifica e molte dimensioni DEIA non coperte. | D10: pp. 3-7, 11-12, 16, 19, 22-23, 26-27 | E10: =[1]Dataset_reporting!U3 -> 2.9090909 | F10: =[1]Dataset_reporting!AD3 -> 2.125
A11: Iveco Group N.V. | B11: Disclosure ESRS strutturata: DEI Policy, DEI Council/HR office, EDGE, KPI workforce/training/pay gap, helpline, human rights assessments, Supplier Code e audit, community target e S4 end-users. | C11: Dimensioni diverse da genere/età prevalentemente policy-based; end-users molto strutturato su safety/accessibility ma meno su inclusive design DEIA. | D11: pp. 17-18, 34, 94-112, 119-123, 126-141, 143-160, 242-243 | E11: =[1]Dataset_reporting!U4 -> 3.8181818 | F11: =[1]Dataset_reporting!AD4 -> 3.25
A13: Campi lasciati vuoti/non compilati | B13: Fater P.IVA; Iveco P.IVA; Fater tipologia analisi materialità; tutti i DEIA website link: non supportati da evidenza nei report o nel dataset.

Sheet Livelli_Maturità_Extended Light
A1: Framework Area | B1: Livello | C1: Descrizione | D1: Key
A2: Strategia | B2: 1 - Awakening | C2: La DEIA non è ancora parte della visione strategica. Le iniziative sono episodiche o di compliance. Manca governance e sponsorship del top management. | D2: • Avviare un assessment iniziale DEIA per mappare punti di forza e gap (breve termine). • Definire e approvare una policy DEIA con sponsor dal vertice (medio termine). | E2: Strategia|1
A3: Strategia | B3: 2 - Improvement | C3: La DEIA è riconosciuta come tema rilevante ma non ancora integrato nella pianificazione strategica. Esistono policy e KPI sperimentali. | D3: • Formalizzare una governance DEIA (comitato o ruolo dedicato) (breve termine). • Collegare la DEIA agli obiettivi ESG e allo scopo/purpose dell’organizzazione (medio termine). | E3: Strategia|2
A4: Strategia | B4: 3 - Consistency | C4: La DEIA è integrata nei piani strategici e sostenuta da leadership attiva. Gli obiettivi sono misurabili e monitorati. | D4: • Rafforzare la misurazione d’impatto e rendicontare i risultati agli stakeholder (medio termine). • Integrare indicatori DEIA nel processo di performance management (lungo termine). | E4: Strategia|3
A5: Strategia | B5: 4 - Embedding | C5: La DEIA è pienamente radicata nel purpose aziendale. Ogni decisione strategica tiene conto dell’impatto inclusivo. | D5: • Implementare un ciclo continuo di miglioramento strategico con revisione annuale DEIA (medio termine). • Diffondere il modello attraverso partnership e benchmarking (lungo termine). | E5: Strategia|4
A6: Processi | B6: 1 - Awakening | C6: I processi non considerano ancora la DEIA. Le pratiche HR e operative sono standard e non equitative. | D6: • Analizzare i processi HR e operativi per individuare bias e barriere (breve termine). • Introdurre criteri minimi di equità e accessibilità nei flussi di lavoro (medio termine). | E6: Processi|1
A7: Processi | B7: 2 - Improvement | C7: Alcuni processi includono elementi DEIA ma senza coerenza o monitoraggio. | D7: • Introdurre procedure di segnalazione e feedback DEIA (breve termine). • Formare HR e manager su selezione equa e comunicazione accessibile (medio termine). | E7: Processi|2
A8: Processi | B8: 3 - Consistency | C8: La DEIA è integrata nei processi organizzativi. I flussi di lavoro sono documentati e revisionati periodicamente. | D8: • Automatizzare il monitoraggio DEIA nei processi chiave (medio termine). • Estendere i criteri di equità alla supply chain e ai fornitori (lungo termine). | E8: Processi|3
A9: Processi | B9: 4 - Embedding | C9: Ogni processo incorpora la DEIA in modo sistematico (equity by design). | D9: • Integrare la DEIA nei sistemi di qualità e risk management (medio termine). • Effettuare audit periodici sull’equità e l’accessibilità dei processi (lungo termine). | E9: Processi|4
A10: Cultura | B10: 1 - Awakening | C10: La cultura organizzativa non riflette ancora valori inclusivi. I comportamenti non sono orientati alla DEIA. | D10: • Avviare workshop di sensibilizzazione e formazione base (breve termine). • Definire un codice etico con principi di rispetto e inclusione (medio termine). | E10: Cultura|1
A11: Cultura | B11: 2 - Improvement | C11: Cresce la consapevolezza, ma la cultura inclusiva non è diffusa in modo uniforme. | D11: • Introdurre programmi di inclusive leadership (breve termine). • Promuovere momenti di ascolto e dialogo interfunzionale (medio termine). | E11: Cultura|2
A12: Cultura | B12: 3 - Consistency | C12: L’inclusione è visibile nel linguaggio e nei comportamenti quotidiani. I leader agiscono come modelli inclusivi. | D12: • Creare community interne o Employee Resource Groups (medio termine). • Riconoscere formalmente i comportamenti inclusivi (lungo termine). | E12: Cultura|3
A13: Cultura | B13: 4 - Embedding | C13: La DEIA è parte integrante del DNA culturale e delle relazioni aziendali. | D13: • Integrare la cultura DEIA nei percorsi di onboarding e sviluppo manageriale (medio termine). • Mantenere viva la cultura inclusiva con storytelling e mentorship (lungo termine). | E13: Cultura|4
... A17: Mercato | B17: 4 - Embedding | C17: L’organizzazione è riconosciuta come modello di inclusione e impatto positivo. | D17: • Consolidare una DEIA value proposition chiara e distintiva (medio termine). • Diffondere standard DEIA a fornitori e clienti (lungo termine). | E17: Mercato|4

Sheet Livelli_Maturità_Extended Deep
A1: Framework Area | B1: Livello | C1: Descrizione | D1: Key
A2: Strategia | B2: 1 - Awakening | C2: La DEIA (Diversità, Equità, Inclusione e Accessibilità) non è ancora parte della visione strategica. Le iniziative sono sporadiche, spesso reattive o di compliance normativa (es. risposte a obblighi o pressioni esterne). Non esiste una visione condivisa sul valore strategico della DEIA né una governance dedicata. Il top management non promuove il tema attivamente, e la responsabilità è percepita come limitata alla funzione HR. La misurazione dell’impatto DEIA è assente o frammentaria. | D2: • Avviare un assessment iniziale DEIA per mappare punti di forza, gap e rischi reputazionali, coinvolgendo leadership, HR e persone chiave (breve termine). • Definire e approvare una policy DEIA aziendale, con chiara sponsorship dal vertice e allineamento alla strategia ESG complessiva (medio termine). • Avviare una campagna di sensibilizzazione interna per diffondere i principi base e il linguaggio comune della DEIA (breve termine). | E2: Strategia|1
A3: Strategia | B3: 2 - Improvement | C3: La DEIA è riconosciuta come tema importante per la reputazione e la sostenibilità, ma non è ancora integrata nei piani strategici o negli obiettivi aziendali. Sono presenti policy o linee guida di base, a volte sviluppate in modo sperimentale, ma senza indicatori consolidati o chiara rendicontazione. Il commitment della leadership è intermittente e non sempre accompagnato da allocazione di risorse. Le decisioni strategiche raramente considerano l’impatto inclusivo, e la DEIA resta una “proprietà” di poche persone motivate. | D3: • Formalizzare una governance DEIA, creando un comitato o un ruolo dedicato con mandato e obiettivi chiari (breve termine). • Collegare la DEIA agli obiettivi ESG e al purpose aziendale, definendo indicatori preliminari e responsabilità di rendicontazione (medio termine). • Sperimentare KPI di diversità e inclusione (es. gender balance, accessibilità, percezione di equità) per testare capacità di monitoraggio (medio termine). | E3: Strategia|2
A4: Strategia | B4: 3 - Consistency | C4: La DEIA è integrata nei piani strategici e sostenuta da una leadership consapevole e coerente. Gli obiettivi sono misurabili, monitorati e collegati alle performance e ai risultati ESG. La governance è chiara, con ruoli e responsabilità definite (es. comitato DEIA o team cross-funzionale). I risultati vengono comunicati internamente, e l’inclusione comincia a essere vista come leva di innovazione e valore organizzativo. Le decisioni strategiche mostrano attenzione alla rappresentanza e all’impatto sociale. | D4: • Rafforzare la misurazione dell’impatto DEIA con indicatori quantitativi e qualitativi integrati nel cruscotto ESG (medio termine). • Integrare la DEIA nella gestione delle performance, collegando obiettivi inclusivi alla valutazione manageriale e ai bonus (lungo termine). • Pubblicare una DEIA Impact Report annuale per stakeholder interni ed esterni (lungo termine). | E4: Strategia|3
A5: Strategia | B5: 4 - Embedding | C5: La DEIA è pienamente radicata nel purpose aziendale e nella visione di lungo periodo. Ogni decisione strategica e organizzativa è valutata anche per il suo impatto inclusivo e sociale. Il top management agisce come sponsor attivo, e la DEIA è parte integrante della governance ESG. Le metriche DEIA sono sistematicamente integrate nella pianificazione, nei bilanci di sostenibilità e nella gestione delle performance. L’organizzazione è riconosciuta per la sua leadership inclusiva e il suo impatto positivo sugli stakeholder interni ed esterni. | D5: • Implementare un ciclo continuo di miglioramento strategico, con revisione annuale del piano DEIA e riallineamento con il purpose e il piano industriale (medio termine). • Diffondere il modello attraverso partnership, benchmarking di settore e adesione a network nazionali o internazionali DEI (lungo termine). • Integrare la DEIA nei processi di decision-making strategico, includendo analisi d’impatto inclusivo per progetti e investimenti (lungo termine). | E5: Strategia|4
A6: Processi | B6: 1 - Awakening | C6: I processi organizzativi e HR non considerano ancora la DEIA. Le pratiche di selezione, sviluppo e valutazione sono standard, ma non equitative: non tengono conto delle differenze e dei bisogni individuali. Non esistono meccanismi di ascolto o revisione dei processi per individuare bias o barriere. Gli strumenti digitali e le comunicazioni interne non garantiscono accessibilità. | D6: • Analizzare i processi HR e operativi per identificare bias, barriere e pratiche discriminatorie, con audit qualitativo (breve termine). • Introdurre criteri minimi di equità e accessibilità nei flussi di lavoro (es. linguaggio, strumenti, orari, ambienti fisici) (medio termine). • Avviare un programma di revisione delle policy HR per garantire parità di trattamento (medio termine). | E6: Processi|1
A7: Processi | B7: 2 - Improvement | C7: Alcuni processi iniziano a includere elementi DEIA (es. linguaggio inclusivo nei bandi, formazione sul bias), ma in modo non sistematico. La revisione dei processi è episodica e spesso dipende da iniziative individuali. Non c’è ancora un monitoraggio strutturato dell’impatto DEIA. Le tecnologie e i flussi di lavoro mostrano progressi, ma la coerenza organizzativa è limitata. | D7: • Creare procedure strutturate per segnalazioni e feedback DEIA, garantendo anonimato e tracciabilità (breve termine). • Formare HR e manager su selezione equa, prevenzione dei bias e comunicazione accessibile (medio termine). • Mappare e aggiornare i processi che hanno impatto sulla DEIA (onboarding, valutazione, promozione) (medio termine). | E7: Processi|2
A8: Processi | B8: 3 - Consistency | C8: La DEIA è integrata nei processi chiave: HR, comunicazione, supply chain e innovazione. I flussi di lavoro sono documentati, verificati periodicamente e progettati per favorire equità e accessibilità. Esistono procedure di segnalazione, piani di miglioramento e criteri DEIA nei processi di valutazione. La leadership di funzione è coinvolta nel garantire che i processi rispettino i principi di inclusione. | D8: • Automatizzare il monitoraggio DEIA nei processi chiave (es. recruiting, compensation, mobility interna) con dashboard di indicatori (medio termine). • Estendere i criteri di equità alla supply chain, introducendo standard DEIA nei contratti e nei processi di vendor evaluation (lungo termine). • Attivare revisioni periodiche dei workflow per garantire coerenza e aggiornamento rispetto alle normative e buone pratiche (lungo termine). | E8: Processi|3
A9: Processi | B9: 4 - Embedding | C9: Ogni processo aziendale incorpora la DEIA in modo strutturale (equity by design). L’equità è un criterio guida nella progettazione, nella gestione e nella revisione dei processi. Le metriche DEIA sono integrate nei sistemi di qualità, audit e risk management. La cultura dell’inclusione è riflessa in ogni fase del ciclo operativo, dalla pianificazione alla delivery. L’organizzazione anticipa le criticità e adotta soluzioni preventive per eliminare bias e barriere. | D9: • Integrare la DEIA nei sistemi di qualità e risk management, rendendola parte dei processi di audit e certificazione (medio termine). • Eseguire audit DEIA regolari sull’equità e sull’accessibilità dei processi, coinvolgendo stakeholder interni ed esterni (lungo termine). • Promuovere un approccio design for inclusion in tutti i nuovi processi e strumenti aziendali (lungo termine). | E9: Processi|4
A10: Cultura | B10: 1 - Awakening | C10: La cultura organizzativa non riflette ancora valori inclusivi. I comportamenti quotidiani e le comunicazioni possono contenere bias o stereotipi. Non esiste consapevolezza diffusa del ruolo della DEIA nella qualità delle relazioni e del clima interno. La sicurezza psicologica è fragile: esprimere opinioni divergenti è percepito come rischioso. | D10: • Avviare workshop di sensibilizzazione e formazione base sulla DEIA, rivolti a tutte le funzioni e livelli (breve termine). • Definire un codice etico con principi di rispetto, equità e inclusione, diffuso e sottoscritto da tutto il personale (medio termine). • Introdurre una sezione DEIA nei canali di comunicazione interna (breve termine). | E10: Cultura|1
A11: Cultura | B11: 2 - Improvement | C11: Cresce la consapevolezza del valore della DEIA, ma i comportamenti inclusivi non sono ancora diffusi in modo coerente. Le iniziative di sensibilizzazione esistono, ma non raggiungono tutti i livelli dell’organizzazione. I leader iniziano a promuovere un linguaggio e uno stile più inclusivi, ma mancano strumenti per misurare i progressi culturali. La gestione dei conflitti o delle diversità di approccio è ancora reattiva. | D11: • Avviare programmi di inclusive leadership, orientati a far emergere comportamenti di ascolto e gestione dei conflitti (breve termine). • Promuovere momenti di dialogo interfunzionale, focus group e storytelling di esperienze inclusive (medio termine). • Inserire la DEIA nei percorsi formativi manageriali (medio termine). | E11: Cultura|2
A12: Cultura | B12: 3 - Consistency | C12: L’inclusione è visibile nei comportamenti, nel linguaggio e nelle relazioni quotidiane. I leader agiscono come modelli di riferimento e promuovono dialogo, rispetto e collaborazione. Le persone percepiscono appartenenza, sicurezza psicologica e pari opportunità di crescita. I comportamenti inclusivi sono riconosciuti e valorizzati anche nei sistemi di performance. La cultura DEIA è sostenuta da programmi formativi e community interne. | D12: • Creare community o Employee Resource Groups (ERG) per promuovere engagement e iniziative di diversità (medio termine). • Riconoscere formalmente i comportamenti inclusivi nei sistemi di valutazione o premi aziendali (lungo termine). • Integrare la DEIA nei programmi di benessere e cultura organizzativa (lungo termine). | E12: Cultura|3
A13: Cultura | B13: 4 - Embedding | C13: La DEIA è parte integrante del DNA organizzativo e delle relazioni. L’inclusione è vissuta come valore condiviso, radicato nel purpose e nelle pratiche di leadership. La diversità è percepita come leva di innovazione, apprendimento e benessere collettivo. La cultura organizzativa si rinnova continuamente attraverso momenti di ascolto, co-progettazione e feedback. | D13: • Integrare la cultura DEIA nei percorsi di onboarding, sviluppo e successione manageriale (medio termine). • Mantenere viva la cultura inclusiva con storytelling interni, mentorship, e giornate tematiche (lungo termine). • Monitorare regolarmente la percezione interna di inclusione e appartenenza con survey periodiche (lungo termine). | E13: Cultura|4
... A17: Mercato | B17: 4 - Embedding | C17: L’organizzazione è riconosciuta come modello di inclusione e impatto positivo sul mercato. L’approccio DEIA è pienamente integrato nella strategia di marketing, innovazione e stakeholder engagement. Le scelte di prodotto, comunicazione e partnership rispecchiano una cultura di equità e rispetto. L’organizzazione guida il cambiamento nel proprio settore, promuovendo standard inclusivi e condivisi lungo tutta la catena del valore. | D17: • Consolidare una DEIA Value Proposition chiara e distintiva, integrata nella narrazione di brand (medio termine). • Diffondere standard DEIA a fornitori, partner e clienti, rendendoli parte del sistema di valutazione e responsabilità sociale (lungo termine). • Comunicare pubblicamente gli impatti positivi generati, in ottica di accountability e trasparenza (lungo termine). | E17: Mercato|4

Sheet Scoring
A1: Scoring per sezione con Pesi e Target
A3: Sezione | B3: Media | D3: Peso | E3: Target
A4: STRATEGY & PURPOSE | B4: =IFERROR(AVERAGEIF(#REF!,"STRATEGY & PURPOSE",#REF!),"") | C4: =IFERROR(AVERAGEIF(#REF!,"STRATEGY & PURPOSE",#REF!),"") | D4: 1 | E4: 3 | F4: =IF($C4="","",$C4*$D4) | G4: =IF($C4="","",$C4-$E4)
A5: GOVERNANCE & AUTHORITY | B5: =IFERROR(AVERAGEIF(#REF!,"GOVERNANCE & AUTHORITY",#REF!),"") | C5: =IFERROR(AVERAGEIF(#REF!,"GOVERNANCE & AUTHORITY",#REF!),"") | D5: 1 | E5: 3 | F5: =IF($C5="","",$C5*$D5) | G5: =IF($C5="","",$C5-$E5)
A6: WORKFLOW & OPERATIONS | B6: =IFERROR(AVERAGEIF(#REF!,"WORKFLOW & OPERATIONS",#REF!),"") | C6: =IFERROR(AVERAGEIF(#REF!,"WORKFLOW & OPERATIONS",#REF!),"") | D6: 1 | E6: 3 | F6: =IF($C6="","",$C6*$D6) | G6: =IF($C6="","",$C6-$E6)
A7: MEETING SYSTEM | B7: =IFERROR(AVERAGEIF(#REF!,"MEETING SYSTEM",#REF!),"") | C7: =IFERROR(AVERAGEIF(#REF!,"MEETING SYSTEM",#REF!),"") | D7: 1 | E7: 3 | F7: =IF($C7="","",$C7*$D7) | G7: =IF($C7="","",$C7-$E7)
A8: INFORMATION FLOW | B8: =IFERROR(AVERAGEIF(#REF!,"INFORMATION FLOW",#REF!),"") | C8: =IFERROR(AVERAGEIF(#REF!,"INFORMATION FLOW",#REF!),"") | D8: 1 | E8: 3 | F8: =IF($C8="","",$C8*$D8) | G8: =IF($C8="","",$C8-$E8)
A9: CULTURE & PEOPLE | B9: =IFERROR(AVERAGEIF(#REF!,"CULTURE & PEOPLE",#REF!),"") | C9: =IFERROR(AVERAGEIF(#REF!,"CULTURE & PEOPLE",#REF!),"") | D9: 1 | E9: 3 | F9: =IF($C9="","",$C9*$D9) | G9: =IF($C9="","",$C9-$E9)
A10: INNOVATION SYSTEM | B10: =IFERROR(AVERAGEIF(#REF!,"INNOVATION SYSTEM",#REF!),"") | C10: =IFERROR(AVERAGEIF(#REF!,"INNOVATION SYSTEM",#REF!),"") | D10: 1 | E10: 3 | F10: =IF($C10="","",$C10*$D10) | G10: =IF($C10="","",$C10-$E10)
A11: MARKET | B11: =IFERROR(AVERAGEIF(#REF!,"MARKET",#REF!),"") | C11: =IFERROR(AVERAGEIF(#REF!,"MARKET",#REF!),"") | D11: 1 | E11: 3 | F11: =IF($C11="","",$C11*$D11) | G11: =IF($C11="","",$C11-$E11)
D13: =IF(B13="","",CHOOSE(ROUND(B13,0),"Awakening","Improvement","Consistency","Embedding"))
D14: =IF(B14="","",CHOOSE(ROUND(B14,0),"Awakening","Improvement","Consistency","Embedding"))

Sheet Dashboard_4Aree
A1: Dashboard – 4 Aree (punteggio, livello e descrizione dinamica)
A3: Strategia | I3: Processi
A4: Media (1-4): | B4: =Macro_Aree!B2 | I4: Media (1-4): | J4: =Macro_Aree!B3
A5: Livello: | B5: =Macro_Aree!C2 | I5: Livello: | J5: =Macro_Aree!C3
A6: Descrizione: | B6: =Macro_Aree!E2 | I6: Descrizione: | J6: =Macro_Aree!E3
B7: =IF(Macro_Aree!D2="","",HYPERLINK("#'Livelli_Maturità_Extended'!A"&MATCH(Macro_Aree!D2,[2]Livelli_Maturità_Extended!E:E,0),"Apri roadmap →")) | J7: =IF(Macro_Aree!D3="","",HYPERLINK("#'Livelli_Maturità_Extended'!A"&MATCH(Macro_Aree!D3,[2]Livelli_Maturità_Extended!E:E,0),"Apri roadmap →"))
A18: Cultura | I18: Mercato
A19: Media (1-4): | B19: =Macro_Aree!B4 | I19: Media (1-4): | J19: =Macro_Aree!B5
A20: Livello: | B20: =Macro_Aree!C4 | I20: Livello: | J20: =Macro_Aree!C5
A21: Descrizione: | B21: =Macro_Aree!E4 | I21: Descrizione: | J21: =Macro_Aree!E5
B22: =IF(Macro_Aree!D4="","",HYPERLINK("#'Livelli_Maturità_Extended'!A"&MATCH(Macro_Aree!D4,[2]Livelli_Maturità_Extended!E:E,0),"Apri roadmap →")) | J22: =IF(Macro_Aree!D5="","",HYPERLINK("#'Livelli_Maturità_Extended'!A"&MATCH(Macro_Aree!D5,[2]Livelli_Maturità_Extended!E:E,0),"Apri roadmap →"))

Sheet Macro_Aree
A1: Area | B1: Media (1–4) | C1: Livello | D1: Key | E1: Descrizione dinamica
A2: Strategia | B2: =IFERROR((SUMIF(#REF!,"STRATEGY & PURPOSE",#REF!)+SUMIF(#REF!,"GOVERNANCE & AUTHORITY",#REF!))/(COUNTIF(#REF!,"STRATEGY & PURPOSE")+COUNTIF(#REF!,"GOVERNANCE & AUTHORITY")),"") | C2: =IF(B2="","",CHOOSE(ROUND(B2,0),"Awakening","Improvement","Consistency","Embedding")) | D2: =IF(B2="","",A2&"|"&ROUND(B2,0)) | E2: =IF(D2="","",INDEX(#REF!,MATCH(D2,#REF!,0)))
A3: Processi | B3: =IFERROR((SUMIF(#REF!,"WORKFLOW & OPERATIONS",#REF!)+SUMIF(#REF!,"INFORMATION FLOW",#REF!)+SUMIF(#REF!,"INNOVATION SYSTEM",#REF!))/(COUNTIF(#REF!,"WORKFLOW & OPERATIONS")+COUNTIF(#REF!,"INFORMATION FLOW")+COUNTIF(#REF!,"INNOVATION SYSTEM")),"") | C3: =IF(B3="","",CHOOSE(ROUND(B3,0),"Awakening","Improvement","Consistency","Embedding")) | D3: =IF(B3="","",A3&"|"&ROUND(B3,0)) | E3: =IF(D3="","",INDEX(#REF!,MATCH(D3,#REF!,0)))
A4: Cultura | B4: =IFERROR((SUMIF(#REF!,"MEETING SYSTEM",#REF!)+SUMIF(#REF!,"CULTURE & PEOPLE",#REF!))/(COUNTIF(#REF!,"MEETING SYSTEM")+COUNTIF(#REF!,"CULTURE & PEOPLE")),"") | C4: =IF(B4="","",CHOOSE(ROUND(B4,0),"Awakening","Improvement","Consistency","Embedding")) | D4: =IF(B4="","",A4&"|"&ROUND(B4,0)) | E4: =IF(D4="","",INDEX(#REF!,MATCH(D4,#REF!,0)))
A5: Mercato | B5: =IFERROR(SUMIF(#REF!,"MARKET",#REF!)/COUNTIF(#REF!,"MARKET"),"") | C5: =IF(B5="","",CHOOSE(ROUND(B5,0),"Awakening","Improvement","Consistency","Embedding")) | D5: =IF(B5="","",A5&"|"&ROUND(B5,0)) | E5: =IF(D5="","",INDEX(#REF!,MATCH(D5,#REF!,0)))

Sheet Chart_Data
A1: Area | B1: Media | C1: Target
A2: Strategia | B2: =Macro_Aree!B2 | C2: 3
A3: Processi | B3: =Macro_Aree!B3 | C3: 3
A4: Cultura | B4: =Macro_Aree!B4 | C4: 3
A5: Mercato | B5: =Macro_Aree!B5 | C5: 3

Sheet Appunti
A1: Tema country: dove è l'headquarter, apporccio culturale, declinazione
A2: Anagrafica (vedi già esistenti tipo Valore D)
A3: Traccia per tutte le dimensioni
A4: Traccia completa
A5: Dati (es. donne assegnatarie di budget, vedi KPI certificazione, persone con disabilità,...)
A6: Fonti BCorp - Great place to work
